graphcompute
examples
